oci_ai_speech_realtime/__init__.py
oci_ai_speech_realtime/ai_service_speech_realtime_client.py
oci_ai_speech_realtime-2.2.0.dist-info/licenses/LICENSE.txt
oci_ai_speech_realtime-2.2.0.dist-info/licenses/THIRD_PARTY_LICENSES.txt
oci_ai_speech_realtime-2.2.0.dist-info/METADATA
oci_ai_speech_realtime-2.2.0.dist-info/WHEEL
oci_ai_speech_realtime-2.2.0.dist-info/top_level.txt
oci_ai_speech_realtime-2.2.0.dist-info/RECORD
