Metadata-Version: 2.4
Name: oci-ai-speech-realtime
Version: 2.2.0
Summary: Oracle Cloud Infrastructure Python SDK for Realtime Speech Service
Home-page: https://docs.oracle.com/en-us/iaas/tools/python/latest/index.html
Author: Oracle
License: Universal Permissive License 1.0
Classifier: Development Status :: 5 - Production/Stable
Classifier: Intended Audience :: Developers
Classifier: License :: OSI Approved :: Universal Permissive License (UPL)
Classifier: Programming Language :: Python :: 3.7
Classifier: Programming Language :: Python :: 3.8
Classifier: Programming Language :: Python :: 3.9
Classifier: Programming Language :: Python :: 3.10
Classifier: Programming Language :: Python :: 3.11
License-File: LICENSE.txt
License-File: THIRD_PARTY_LICENSES.txt
Requires-Dist: oci>=2.159.0
Requires-Dist: websockets>=11.0.3
Provides-Extra: dev
Requires-Dist: pip-tools; extra == "dev"
Requires-Dist: build; extra == "dev"
Requires-Dist: twine; extra == "dev"
Dynamic: author
Dynamic: classifier
Dynamic: description
Dynamic: description-content-type
Dynamic: home-page
Dynamic: license
Dynamic: license-file
Dynamic: provides-extra
Dynamic: requires-dist
Dynamic: summary
